MANIFEST.in
README.md
package_info.json
requirements.txt
setup.py
th2_grpc_crawler_data_processor/__init__.py
th2_grpc_crawler_data_processor/crawler_data_processor.proto
th2_grpc_crawler_data_processor/crawler_data_processor_pb2.py
th2_grpc_crawler_data_processor/crawler_data_processor_pb2.pyi
th2_grpc_crawler_data_processor/crawler_data_processor_pb2_grpc.py
th2_grpc_crawler_data_processor/data_processor_service.py
th2_grpc_crawler_data_processor/py.typed
th2_grpc_crawler_data_processor.egg-info/PKG-INFO
th2_grpc_crawler_data_processor.egg-info/SOURCES.txt
th2_grpc_crawler_data_processor.egg-info/dependency_links.txt
th2_grpc_crawler_data_processor.egg-info/requires.txt
th2_grpc_crawler_data_processor.egg-info/top_level.txt