Metadata-Version: 2.1
Name: th2-grpc-crawler-data-processor
Version: 0.3.2
Summary: th2_grpc_crawler_data_processor
Home-page: https://github.com/th2-net/th2-grpc-crawler-data-processor
Author: TH2-devs
Author-email: th2-devs@exactprosystems.com
License: Apache License 2.0
Platform: UNKNOWN
Requires-Python: >=3.7
